happy_learning/__init__.py
happy_learning/arbitrary_modeling.py
happy_learning/chaid_decision_tree.py
happy_learning/data_miner.py
happy_learning/deep_q_learning.py
happy_learning/environment_modeling.py
happy_learning/evaluate_machine_learning.py
happy_learning/feature_engineer.py
happy_learning/feature_learning.py
happy_learning/feature_selector.py
happy_learning/genetic_algorithm.py
happy_learning/missing_data_analysis.py
happy_learning/multiple_imputation.py
happy_learning/neural_network_generator_torch.py
happy_learning/neural_network_torch.py
happy_learning/sampler.py
happy_learning/self_taught_short_text_clustering.py
happy_learning/supervised_machine_learning.py
happy_learning/swarm_intelligence.py
happy_learning/text_clustering.py
happy_learning/text_clustering_generator.py
happy_learning/text_miner.py
happy_learning/utils.py
happy_learning-0.5.0.dist-info/LICENSE
happy_learning-0.5.0.dist-info/METADATA
happy_learning-0.5.0.dist-info/WHEEL
happy_learning-0.5.0.dist-info/top_level.txt
happy_learning-0.5.0.dist-info/RECORD
