Metadata-Version: 2.1
Name: happy-learning
Version: 0.5.0
Summary: Toolbox for reinforced developing of machine learning models (as proof-of-concept)
Home-page: https://github.com/GianniBalistreri/happy_learning
Author: Gianni Francesco Balistreri
Author-email: gbalistreri@gmx.de
License: GNU
Keywords: feature-engineering feature-selection evolutionary-algorithm machine-learning automl reinforcement-learning deep-learning shapley clustering pytorch
Classifier: Programming Language :: Python :: 3
Classifier: Programming Language :: Python :: 3.6
Classifier: Programming Language :: Python :: 3.7
Classifier: Programming Language :: Python :: 3.8
Classifier: Operating System :: OS Independent
Requires-Python: >=3.6
License-File: LICENSE
Requires-Dist: catboost (==0.24.2)
Requires-Dist: Chaid (==5.3.0)
Requires-Dist: combo (==0.1.1)
Requires-Dist: dask-ml (==1.7.0)
Requires-Dist: easyexplore (==0.7.4)
Requires-Dist: emoji (==0.6.0)
Requires-Dist: fast-gsdmm (==0.0.1)
Requires-Dist: gensim (==3.8.3)
Requires-Dist: geocoder (==1.38.1)
Requires-Dist: googletrans (==3.0.0)
Requires-Dist: nltk (==3.5)
Requires-Dist: mlflow (==1.24.0)
Requires-Dist: protobuf (==3.20.3)
Requires-Dist: pygam (==0.8.0)
Requires-Dist: requests (==2.24.0)
Requires-Dist: sentence-transformers (==0.4.1)
Requires-Dist: spacy (==2.3.2)
Requires-Dist: sqlalchemy (==1.3.19)
Requires-Dist: statsmodels (==0.12.0)
Requires-Dist: torch (==1.7.0)
Requires-Dist: torchtext (==0.8.0)
Requires-Dist: xgboost (==1.7.5)
